dotter/__init__.py
dotter/__main__.py
dotter/colors.py
dotter/model.py
dotter/sync_plan.py
dotter/utils.py
nl_dotter-0.2.2.dist-info/METADATA
nl_dotter-0.2.2.dist-info/WHEEL
nl_dotter-0.2.2.dist-info/entry_points.txt
nl_dotter-0.2.2.dist-info/RECORD
