Metadata-Version: 2.1
Name: nl-dotter
Version: 0.2.2
Summary: A dotfile link farm manager.
Home-page: https://github.com/NonLogicalDev/cli.dotter
License: MIT
Author: nonlogicaldev
Requires-Python: >=3.11,<4.0
Classifier: Development Status :: 3 - Alpha
Classifier: License :: OSI Approved :: MIT License
Classifier: Programming Language :: Python :: 3
Classifier: Programming Language :: Python :: 3.11
Requires-Dist: click (>=8.1.7,<9.0.0)
Requires-Dist: pydantic (>=2.7.0,<3.0.0)
Project-URL: Repository, https://github.com/NonLogicalDev/cli.dotter
